<?xml version="1.0" encoding="UTF-8" standalone="no"?>
<Configuration>
  <Components>
    <UniqueComponent dnOrder="0" id="adc">
      <Symbols dnOrder="0">
        <Float dnOrder="0" id="ADC_TCLK">
          <Values dnOrder="0">
            <Dynamic dnOrder="0" id="adc" value="150.0"/>
          </Values>
        </Float>
      </Symbols>
    </UniqueComponent>
    <UniqueComponent dnOrder="1" id="core">
      <Symbols dnOrder="0">
        <Boolean dnOrder="0" id="ADC_CLOCK_ENABLE">
          <Values dnOrder="0">
            <Dynamic dnOrder="0" id="adc" value="true"/>
          </Values>
        </Boolean>
        <Integer dnOrder="1" id="ADC_CLOCK_FREQUENCY">
          <Values dnOrder="0">
            <Dynamic dnOrder="0" id="core" value="40000000"/>
          </Values>
        </Integer>
        <String dnOrder="2" id="BSP_PIN_0_MODE">
          <Values dnOrder="0">
            <User dnOrder="0" value="DIGITAL"/>
          </Values>
        </String>
        <String dnOrder="3" id="BSP_PIN_1_MODE">
          <Values dnOrder="0">
            <User dnOrder="0" value="DIGITAL"/>
          </Values>
        </String>
        <String dnOrder="4" id="BSP_PIN_22_FUNCTION_NAME">
          <Values dnOrder="0">
            <User dnOrder="0" value="GPIO_RB3"/>
          </Values>
        </String>
        <String dnOrder="5" id="BSP_PIN_22_FUNCTION_TYPE">
          <Values dnOrder="0">
            <User dnOrder="0" value="GPIO"/>
          </Values>
        </String>
        <String dnOrder="6" id="BSP_PIN_23_FUNCTION_NAME">
          <Values dnOrder="0">
            <User dnOrder="0" value="GPIO_RB2"/>
          </Values>
        </String>
        <String dnOrder="7" id="BSP_PIN_23_FUNCTION_TYPE">
          <Values dnOrder="0">
            <User dnOrder="0" value="GPIO"/>
          </Values>
        </String>
        <String dnOrder="8" id="BSP_PIN_24_FUNCTION_NAME">
          <Values dnOrder="0">
            <User dnOrder="0" value="GPIO_RB1"/>
          </Values>
        </String>
        <String dnOrder="9" id="BSP_PIN_24_FUNCTION_TYPE">
          <Values dnOrder="0">
            <User dnOrder="0" value="GPIO"/>
          </Values>
        </String>
        <String dnOrder="10" id="BSP_PIN_25_DIR">
          <Values dnOrder="0">
            <User dnOrder="0" value=""/>
          </Values>
        </String>
        <String dnOrder="11" id="BSP_PIN_25_FUNCTION_NAME">
          <Values dnOrder="0">
            <User dnOrder="0" value="GPIO_RB0"/>
          </Values>
        </String>
        <String dnOrder="12" id="BSP_PIN_25_FUNCTION_TYPE">
          <Values dnOrder="0">
            <User dnOrder="0" value="GPIO"/>
          </Values>
        </String>
        <String dnOrder="13" id="BSP_PIN_2_MODE">
          <Values dnOrder="0">
            <User dnOrder="0" value="DIGITAL"/>
          </Values>
        </String>
        <String dnOrder="14" id="BSP_PIN_2_PU">
          <Values dnOrder="0">
            <User dnOrder="0" value="True"/>
          </Values>
        </String>
        <String dnOrder="15" id="BSP_PIN_32_FUNCTION_TYPE">
          <Values dnOrder="0">
            <User dnOrder="0" value="AN8"/>
          </Values>
        </String>
        <String dnOrder="16" id="BSP_PIN_3_MODE">
          <Values dnOrder="0">
            <User dnOrder="0" value="DIGITAL"/>
          </Values>
        </String>
        <String dnOrder="17" id="BSP_PIN_3_PU">
          <Values dnOrder="0">
            <User dnOrder="0" value="True"/>
          </Values>
        </String>
        <String dnOrder="18" id="BSP_PIN_4_PU">
          <Values dnOrder="0">
            <User dnOrder="0" value="True"/>
          </Values>
        </String>
        <String dnOrder="19" id="BSP_PIN_52_FUNCTION_TYPE">
          <Values dnOrder="0">
            <User dnOrder="0" value="U1RX"/>
          </Values>
        </String>
        <String dnOrder="20" id="BSP_PIN_53_FUNCTION_TYPE">
          <Values dnOrder="0">
            <User dnOrder="0" value="U1TX"/>
          </Values>
        </String>
        <String dnOrder="21" id="BSP_PIN_58_FUNCTION_TYPE">
          <Values dnOrder="0">
            <User dnOrder="0" value="SCL2"/>
          </Values>
        </String>
        <String dnOrder="22" id="BSP_PIN_59_FUNCTION_TYPE">
          <Values dnOrder="0">
            <User dnOrder="0" value="SDA2"/>
          </Values>
        </String>
        <String dnOrder="23" id="BSP_PIN_5_PU">
          <Values dnOrder="0">
            <User dnOrder="0" value="True"/>
          </Values>
        </String>
        <String dnOrder="24" id="BSP_PIN_93_DIR">
          <Values dnOrder="0">
            <User dnOrder="0" value="Out"/>
          </Values>
        </String>
        <String dnOrder="25" id="BSP_PIN_93_FUNCTION_NAME">
          <Values dnOrder="0">
            <User dnOrder="0" value="GPIO_RE0"/>
          </Values>
        </String>
        <String dnOrder="26" id="BSP_PIN_93_FUNCTION_TYPE">
          <Values dnOrder="0">
            <User dnOrder="0" value="GPIO"/>
          </Values>
        </String>
        <String dnOrder="27" id="BSP_PIN_93_LAT">
          <Values dnOrder="0">
            <User dnOrder="0" value=""/>
          </Values>
        </String>
        <String dnOrder="28" id="BSP_PIN_94_DIR">
          <Values dnOrder="0">
            <User dnOrder="0" value="Out"/>
          </Values>
        </String>
        <String dnOrder="29" id="BSP_PIN_94_FUNCTION_NAME">
          <Values dnOrder="0">
            <User dnOrder="0" value="GPIO_RE1"/>
          </Values>
        </String>
        <String dnOrder="30" id="BSP_PIN_94_FUNCTION_TYPE">
          <Values dnOrder="0">
            <User dnOrder="0" value="GPIO"/>
          </Values>
        </String>
        <String dnOrder="31" id="BSP_PIN_98_DIR">
          <Values dnOrder="0">
            <User dnOrder="0" value="Out"/>
          </Values>
        </String>
        <String dnOrder="32" id="BSP_PIN_98_FUNCTION_NAME">
          <Values dnOrder="0">
            <User dnOrder="0" value="GPIO_RE2"/>
          </Values>
        </String>
        <String dnOrder="33" id="BSP_PIN_98_FUNCTION_TYPE">
          <Values dnOrder="0">
            <User dnOrder="0" value="GPIO"/>
          </Values>
        </String>
        <String dnOrder="34" id="BSP_PIN_99_DIR">
          <Values dnOrder="0">
            <User dnOrder="0" value="Out"/>
          </Values>
        </String>
        <String dnOrder="35" id="BSP_PIN_99_FUNCTION_NAME">
          <Values dnOrder="0">
            <User dnOrder="0" value="GPIO_RE3"/>
          </Values>
        </String>
        <String dnOrder="36" id="BSP_PIN_99_FUNCTION_TYPE">
          <Values dnOrder="0">
            <User dnOrder="0" value="GPIO"/>
          </Values>
        </String>
        <Integer dnOrder="37" id="CAN1_CLOCK_FREQUENCY">
          <Values dnOrder="0">
            <Dynamic dnOrder="0" id="core" value="0"/>
          </Values>
        </Integer>
        <Integer dnOrder="38" id="CAN2_CLOCK_FREQUENCY">
          <Values dnOrder="0">
            <Dynamic dnOrder="0" id="core" value="0"/>
          </Values>
        </Integer>
        <Integer dnOrder="39" id="CMP1_CLOCK_FREQUENCY">
          <Values dnOrder="0">
            <Dynamic dnOrder="0" id="core" value="0"/>
          </Values>
        </Integer>
        <Integer dnOrder="40" id="CMP2_CLOCK_FREQUENCY">
          <Values dnOrder="0">
            <Dynamic dnOrder="0" id="core" value="0"/>
          </Values>
        </Integer>
        <KeyValueSet dnOrder="41" id="COMPILER_CHOICE">
          <Values dnOrder="0">
            <Dynamic dnOrder="0" id="core" value="0"/>
          </Values>
        </KeyValueSet>
        <Combo dnOrder="42" id="CONFIG_FNOSC">
          <Values dnOrder="0">
            <User dnOrder="0" value="PRIPLL"/>
          </Values>
        </Combo>
        <Combo dnOrder="43" id="CONFIG_FPBDIV">
          <Values dnOrder="0">
            <User dnOrder="0" value="DIV_2"/>
          </Values>
        </Combo>
        <Combo dnOrder="44" id="CONFIG_FPLLIDIV">
          <Values dnOrder="0">
            <User dnOrder="0" value="DIV_2"/>
          </Values>
        </Combo>
        <Combo dnOrder="45" id="CONFIG_FPLLMUL">
          <Values dnOrder="0">
            <User dnOrder="0" value="MUL_20"/>
          </Values>
        </Combo>
        <Combo dnOrder="46" id="CONFIG_POSCMOD">
          <Values dnOrder="0">
            <User dnOrder="0" value="XT"/>
          </Values>
        </Combo>
        <KeyValueSet dnOrder="47" id="CONFIG_SYS_CLK_FRCDIV">
          <Values dnOrder="0">
            <User dnOrder="0" value="6"/>
          </Values>
        </KeyValueSet>
        <String dnOrder="48" id="CONFIG_SYS_CLK_PBCLK_FREQ">
          <Values dnOrder="0">
            <User dnOrder="0" value="40000000"/>
          </Values>
        </String>
        <Combo dnOrder="49" id="CONFIG_UPLLEN">
          <Values dnOrder="0">
            <User dnOrder="0" value="OFF"/>
          </Values>
        </Combo>
        <Combo dnOrder="50" id="CONFIG_UPLLIDIV">
          <Values dnOrder="0">
            <User dnOrder="0" value="DIV_2"/>
          </Values>
        </Combo>
        <Boolean dnOrder="51" id="CORE_TIMER_INTERRUPT_ENABLE">
          <Values dnOrder="0">
            <Dynamic dnOrder="0" id="core_timer" value="false"/>
          </Values>
        </Boolean>
        <Boolean dnOrder="52" id="CORE_TIMER_INTERRUPT_ENABLE_UPDATE">
          <Values dnOrder="0">
            <Dynamic dnOrder="0" id="core" value="true"/>
          </Values>
        </Boolean>
        <String dnOrder="53" id="CORE_TIMER_INTERRUPT_HANDLER">
          <Values dnOrder="0">
            <Dynamic dnOrder="0" id="core_timer" value="CORE_TIMER_Handler"/>
          </Values>
        </String>
        <Boolean dnOrder="54" id="CORE_TIMER_INTERRUPT_HANDLER_LOCK">
          <Values dnOrder="0">
            <Dynamic dnOrder="0" id="core_timer" value="false"/>
          </Values>
        </Boolean>
        <Integer dnOrder="55" id="CVR_CLOCK_FREQUENCY">
          <Values dnOrder="0">
            <Dynamic dnOrder="0" id="core" value="0"/>
          </Values>
        </Integer>
        <String dnOrder="56" id="DCH0_CON_CHPRI_VALUE">
          <Values dnOrder="0">
            <Dynamic dnOrder="0" id="core" value="0"/>
          </Values>
        </String>
        <Hex dnOrder="57" id="DCH0_CON_VALUE">
          <Values dnOrder="0">
            <Dynamic dnOrder="0" id="core" value="0"/>
          </Values>
        </Hex>
        <Integer dnOrder="58" id="DCH0_ECON_SIRQEN_VALUE">
          <Values dnOrder="0">
            <Dynamic dnOrder="0" id="core" value="1"/>
          </Values>
        </Integer>
        <Hex dnOrder="59" id="DCH0_ECON_VALUE">
          <Values dnOrder="0">
            <Dynamic dnOrder="0" id="core" value="7184"/>
          </Values>
        </Hex>
        <String dnOrder="60" id="DCH1_CON_CHPRI_VALUE">
          <Values dnOrder="0">
            <Dynamic dnOrder="0" id="core" value="0"/>
          </Values>
        </String>
        <Hex dnOrder="61" id="DCH1_CON_VALUE">
          <Values dnOrder="0">
            <Dynamic dnOrder="0" id="core" value="0"/>
          </Values>
        </Hex>
        <Integer dnOrder="62" id="DCH1_ECON_SIRQEN_VALUE">
          <Values dnOrder="0">
            <Dynamic dnOrder="0" id="core" value="1"/>
          </Values>
        </Integer>
        <Hex dnOrder="63" id="DCH1_ECON_VALUE">
          <Values dnOrder="0">
            <Dynamic dnOrder="0" id="core" value="6928"/>
          </Values>
        </Hex>
        <Boolean dnOrder="64" id="DMAC_CHAN0_ENBL">
          <Values dnOrder="0">
            <User dnOrder="0" value="true"/>
          </Values>
        </Boolean>
        <Boolean dnOrder="65" id="DMAC_CHAN1_ENBL">
          <Values dnOrder="0">
            <User dnOrder="0" value="true"/>
          </Values>
        </Boolean>
        <File dnOrder="66" id="DMAC_HEADER">
          <Attributes dnOrder="0">
            <Boolean dnOrder="0" id="enabled">
              <Value dnOrder="0">true</Value>
            </Boolean>
          </Attributes>
        </File>
        <Integer dnOrder="67" id="DMAC_HIGHEST_CHANNEL">
          <Values dnOrder="0">
            <Dynamic dnOrder="0" id="core" value="2"/>
          </Values>
        </Integer>
        <Combo dnOrder="68" id="DMAC_REQUEST_0_SOURCE">
          <Values dnOrder="0">
            <User dnOrder="0" value="UART1_TX"/>
          </Values>
        </Combo>
        <Integer dnOrder="69" id="DMAC_REQUEST_0_SOURCE_VALUE">
          <Values dnOrder="0">
            <Dynamic dnOrder="0" id="core" value="28"/>
          </Values>
        </Integer>
        <Combo dnOrder="70" id="DMAC_REQUEST_1_SOURCE">
          <Values dnOrder="0">
            <User dnOrder="0" value="UART1_RX"/>
          </Values>
        </Combo>
        <Integer dnOrder="71" id="DMAC_REQUEST_1_SOURCE_VALUE">
          <Values dnOrder="0">
            <Dynamic dnOrder="0" id="core" value="27"/>
          </Values>
        </Integer>
        <File dnOrder="72" id="DMAC_SOURCE">
          <Attributes dnOrder="0">
            <Boolean dnOrder="0" id="enabled">
              <Value dnOrder="0">true</Value>
            </Boolean>
          </Attributes>
        </File>
        <File dnOrder="73" id="DMAC_SYS_DEF">
          <Attributes dnOrder="0">
            <Boolean dnOrder="0" id="enabled">
              <Value dnOrder="0">true</Value>
            </Boolean>
          </Attributes>
        </File>
        <File dnOrder="74" id="DMAC_SYS_INIT">
          <Attributes dnOrder="0">
            <Boolean dnOrder="0" id="enabled">
              <Value dnOrder="0">true</Value>
            </Boolean>
          </Attributes>
        </File>
        <Boolean dnOrder="75" id="DMA_0_INTERRUPT_ENABLE">
          <Values dnOrder="0">
            <Dynamic dnOrder="0" id="core" value="true"/>
          </Values>
        </Boolean>
        <Boolean dnOrder="76" id="DMA_0_INTERRUPT_ENABLE_UPDATE">
          <Values dnOrder="0">
            <Dynamic dnOrder="0" id="core" value="false"/>
          </Values>
        </Boolean>
        <String dnOrder="77" id="DMA_0_INTERRUPT_HANDLER">
          <Values dnOrder="0">
            <Dynamic dnOrder="0" id="core" value="DMA_0_InterruptHandler"/>
          </Values>
        </String>
        <Boolean dnOrder="78" id="DMA_0_INTERRUPT_HANDLER_LOCK">
          <Values dnOrder="0">
            <Dynamic dnOrder="0" id="core" value="true"/>
          </Values>
        </Boolean>
        <Boolean dnOrder="79" id="DMA_1_INTERRUPT_ENABLE">
          <Values dnOrder="0">
            <Dynamic dnOrder="0" id="core" value="true"/>
          </Values>
        </Boolean>
        <Boolean dnOrder="80" id="DMA_1_INTERRUPT_ENABLE_UPDATE">
          <Values dnOrder="0">
            <Dynamic dnOrder="0" id="core" value="false"/>
          </Values>
        </Boolean>
        <String dnOrder="81" id="DMA_1_INTERRUPT_HANDLER">
          <Values dnOrder="0">
            <Dynamic dnOrder="0" id="core" value="DMA_1_InterruptHandler"/>
          </Values>
        </String>
        <Boolean dnOrder="82" id="DMA_1_INTERRUPT_HANDLER_LOCK">
          <Values dnOrder="0">
            <Dynamic dnOrder="0" id="core" value="true"/>
          </Values>
        </Boolean>
        <Boolean dnOrder="83" id="DMA_ENABLE">
          <Values dnOrder="0">
            <Dynamic dnOrder="0" id="core" value="true"/>
          </Values>
        </Boolean>
        <Boolean dnOrder="84" id="EVIC_0_ENABLE">
          <Values dnOrder="0">
            <Dynamic dnOrder="0" id="core" value="false"/>
          </Values>
        </Boolean>
        <Boolean dnOrder="85" id="EVIC_0_HANDLER_LOCK">
          <Values dnOrder="0">
            <Dynamic dnOrder="0" id="core" value="false"/>
          </Values>
        </Boolean>
        <String dnOrder="86" id="EVIC_0_INTERRUPT_HANDLER">
          <Values dnOrder="0">
            <Dynamic dnOrder="0" id="core" value="CORE_TIMER_Handler"/>
          </Values>
        </String>
        <Boolean dnOrder="87" id="EVIC_12_ENABLE">
          <Values dnOrder="0">
            <Dynamic dnOrder="0" id="core" value="true"/>
          </Values>
        </Boolean>
        <Boolean dnOrder="88" id="EVIC_12_HANDLER_LOCK">
          <Values dnOrder="0">
            <Dynamic dnOrder="0" id="core" value="true"/>
          </Values>
        </Boolean>
        <String dnOrder="89" id="EVIC_12_INTERRUPT_HANDLER">
          <Values dnOrder="0">
            <Dynamic dnOrder="0" id="core" value="TIMER_3_InterruptHandler"/>
          </Values>
        </String>
        <Boolean dnOrder="90" id="EVIC_16_ENABLE">
          <Values dnOrder="0">
            <Dynamic dnOrder="0" id="core" value="true"/>
          </Values>
        </Boolean>
        <Boolean dnOrder="91" id="EVIC_16_HANDLER_LOCK">
          <Values dnOrder="0">
            <Dynamic dnOrder="0" id="core" value="true"/>
          </Values>
        </Boolean>
        <String dnOrder="92" id="EVIC_16_INTERRUPT_HANDLER">
          <Values dnOrder="0">
            <Dynamic dnOrder="0" id="core" value="TIMER_4_InterruptHandler"/>
          </Values>
        </String>
        <Boolean dnOrder="93" id="EVIC_24_2_ENABLE">
          <Values dnOrder="0">
            <Dynamic dnOrder="0" id="core" value="true"/>
          </Values>
        </Boolean>
        <Boolean dnOrder="94" id="EVIC_24_2_HANDLER_LOCK">
          <Values dnOrder="0">
            <Dynamic dnOrder="0" id="core" value="true"/>
          </Values>
        </Boolean>
        <String dnOrder="95" id="EVIC_24_2_INTERRUPT_HANDLER">
          <Values dnOrder="0">
            <Dynamic dnOrder="0" id="core" value="UART_1_InterruptHandler"/>
          </Values>
        </String>
        <Boolean dnOrder="96" id="EVIC_33_ENABLE">
          <Values dnOrder="0">
            <Dynamic dnOrder="0" id="core" value="true"/>
          </Values>
        </Boolean>
        <Boolean dnOrder="97" id="EVIC_33_HANDLER_LOCK">
          <Values dnOrder="0">
            <Dynamic dnOrder="0" id="core" value="true"/>
          </Values>
        </Boolean>
        <String dnOrder="98" id="EVIC_33_INTERRUPT_HANDLER">
          <Values dnOrder="0">
            <Dynamic dnOrder="0" id="core" value="I2C_2_InterruptHandler"/>
          </Values>
        </String>
        <Boolean dnOrder="99" id="EVIC_36_ENABLE">
          <Values dnOrder="0">
            <Dynamic dnOrder="0" id="core" value="true"/>
          </Values>
        </Boolean>
        <Boolean dnOrder="100" id="EVIC_36_HANDLER_LOCK">
          <Values dnOrder="0">
            <Dynamic dnOrder="0" id="core" value="true"/>
          </Values>
        </Boolean>
        <String dnOrder="101" id="EVIC_36_INTERRUPT_HANDLER">
          <Values dnOrder="0">
            <Dynamic dnOrder="0" id="core" value="DMA_0_InterruptHandler"/>
          </Values>
        </String>
        <Boolean dnOrder="102" id="EVIC_37_ENABLE">
          <Values dnOrder="0">
            <Dynamic dnOrder="0" id="core" value="true"/>
          </Values>
        </Boolean>
        <Boolean dnOrder="103" id="EVIC_37_HANDLER_LOCK">
          <Values dnOrder="0">
            <Dynamic dnOrder="0" id="core" value="true"/>
          </Values>
        </Boolean>
        <String dnOrder="104" id="EVIC_37_INTERRUPT_HANDLER">
          <Values dnOrder="0">
            <Dynamic dnOrder="0" id="core" value="DMA_1_InterruptHandler"/>
          </Values>
        </String>
        <Boolean dnOrder="105" id="EVIC_8_ENABLE">
          <Values dnOrder="0">
            <Dynamic dnOrder="0" id="core" value="false"/>
          </Values>
        </Boolean>
        <Boolean dnOrder="106" id="EVIC_8_HANDLER_LOCK">
          <Values dnOrder="0">
            <Dynamic dnOrder="0" id="core" value="false"/>
          </Values>
        </Boolean>
        <String dnOrder="107" id="EVIC_8_INTERRUPT_HANDLER">
          <Values dnOrder="0">
            <Dynamic dnOrder="0" id="core" value="TIMER_2_Handler"/>
          </Values>
        </String>
        <Integer dnOrder="108" id="I2C1_CLOCK_FREQUENCY">
          <Values dnOrder="0">
            <Dynamic dnOrder="0" id="core" value="0"/>
          </Values>
        </Integer>
        <Boolean dnOrder="109" id="I2C2_CLOCK_ENABLE">
          <Values dnOrder="0">
            <Dynamic dnOrder="0" id="i2c2" value="true"/>
          </Values>
        </Boolean>
        <Integer dnOrder="110" id="I2C2_CLOCK_FREQUENCY">
          <Values dnOrder="0">
            <Dynamic dnOrder="0" id="core" value="40000000"/>
          </Values>
        </Integer>
        <Integer dnOrder="111" id="I2C3_CLOCK_FREQUENCY">
          <Values dnOrder="0">
            <Dynamic dnOrder="0" id="core" value="0"/>
          </Values>
        </Integer>
        <Integer dnOrder="112" id="I2C4_CLOCK_FREQUENCY">
          <Values dnOrder="0">
            <Dynamic dnOrder="0" id="core" value="0"/>
          </Values>
        </Integer>
        <Integer dnOrder="113" id="I2C5_CLOCK_FREQUENCY">
          <Values dnOrder="0">
            <Dynamic dnOrder="0" id="core" value="0"/>
          </Values>
        </Integer>
        <Boolean dnOrder="114" id="I2C_2_INTERRUPT_ENABLE">
          <Values dnOrder="0">
            <Dynamic dnOrder="0" id="i2c2" value="true"/>
          </Values>
        </Boolean>
        <Boolean dnOrder="115" id="I2C_2_INTERRUPT_ENABLE_UPDATE">
          <Values dnOrder="0">
            <Dynamic dnOrder="0" id="core" value="false"/>
          </Values>
        </Boolean>
        <String dnOrder="116" id="I2C_2_INTERRUPT_HANDLER">
          <Values dnOrder="0">
            <Dynamic dnOrder="0" id="i2c2" value="I2C_2_InterruptHandler"/>
          </Values>
        </String>
        <Boolean dnOrder="117" id="I2C_2_INTERRUPT_HANDLER_LOCK">
          <Values dnOrder="0">
            <Dynamic dnOrder="0" id="i2c2" value="true"/>
          </Values>
        </Boolean>
        <Integer dnOrder="118" id="ICAP1_CLOCK_FREQUENCY">
          <Values dnOrder="0">
            <Dynamic dnOrder="0" id="core" value="0"/>
          </Values>
        </Integer>
        <Integer dnOrder="119" id="ICAP2_CLOCK_FREQUENCY">
          <Values dnOrder="0">
            <Dynamic dnOrder="0" id="core" value="0"/>
          </Values>
        </Integer>
        <Integer dnOrder="120" id="ICAP3_CLOCK_FREQUENCY">
          <Values dnOrder="0">
            <Dynamic dnOrder="0" id="core" value="0"/>
          </Values>
        </Integer>
        <Integer dnOrder="121" id="ICAP4_CLOCK_FREQUENCY">
          <Values dnOrder="0">
            <Dynamic dnOrder="0" id="core" value="0"/>
          </Values>
        </Integer>
        <Integer dnOrder="122" id="ICAP5_CLOCK_FREQUENCY">
          <Values dnOrder="0">
            <Dynamic dnOrder="0" id="core" value="0"/>
          </Values>
        </Integer>
        <Integer dnOrder="123" id="OCMP1_CLOCK_FREQUENCY">
          <Values dnOrder="0">
            <Dynamic dnOrder="0" id="core" value="0"/>
          </Values>
        </Integer>
        <Integer dnOrder="124" id="OCMP2_CLOCK_FREQUENCY">
          <Values dnOrder="0">
            <Dynamic dnOrder="0" id="core" value="0"/>
          </Values>
        </Integer>
        <Integer dnOrder="125" id="OCMP3_CLOCK_FREQUENCY">
          <Values dnOrder="0">
            <Dynamic dnOrder="0" id="core" value="0"/>
          </Values>
        </Integer>
        <Integer dnOrder="126" id="OCMP4_CLOCK_FREQUENCY">
          <Values dnOrder="0">
            <Dynamic dnOrder="0" id="core" value="0"/>
          </Values>
        </Integer>
        <Integer dnOrder="127" id="OCMP5_CLOCK_FREQUENCY">
          <Values dnOrder="0">
            <Dynamic dnOrder="0" id="core" value="0"/>
          </Values>
        </Integer>
        <Integer dnOrder="128" id="PMP_CLOCK_FREQUENCY">
          <Values dnOrder="0">
            <Dynamic dnOrder="0" id="core" value="0"/>
          </Values>
        </Integer>
        <Integer dnOrder="129" id="RTCC_CLOCK_FREQUENCY">
          <Values dnOrder="0">
            <Dynamic dnOrder="0" id="core" value="0"/>
          </Values>
        </Integer>
        <Integer dnOrder="130" id="SPI1_CLOCK_FREQUENCY">
          <Values dnOrder="0">
            <Dynamic dnOrder="0" id="core" value="0"/>
          </Values>
        </Integer>
        <Integer dnOrder="131" id="SPI2_CLOCK_FREQUENCY">
          <Values dnOrder="0">
            <Dynamic dnOrder="0" id="core" value="0"/>
          </Values>
        </Integer>
        <Integer dnOrder="132" id="SPI3_CLOCK_FREQUENCY">
          <Values dnOrder="0">
            <Dynamic dnOrder="0" id="core" value="0"/>
          </Values>
        </Integer>
        <Integer dnOrder="133" id="SPI4_CLOCK_FREQUENCY">
          <Values dnOrder="0">
            <Dynamic dnOrder="0" id="core" value="0"/>
          </Values>
        </Integer>
        <Hex dnOrder="134" id="SYS_PORT_AD1PCFG">
          <Values dnOrder="0">
            <Dynamic dnOrder="0" id="core" value="15"/>
          </Values>
        </Hex>
        <Hex dnOrder="135" id="SYS_PORT_B_TRIS">
          <Values dnOrder="0">
            <Dynamic dnOrder="0" id="core" value="0"/>
          </Values>
        </Hex>
        <Hex dnOrder="136" id="SYS_PORT_CNPUE">
          <Values dnOrder="0">
            <Dynamic dnOrder="0" id="core" value="60"/>
          </Values>
        </Hex>
        <Hex dnOrder="137" id="SYS_PORT_E_LAT">
          <Values dnOrder="0">
            <Dynamic dnOrder="0" id="core" value="0"/>
          </Values>
        </Hex>
        <Hex dnOrder="138" id="SYS_PORT_E_TRIS">
          <Values dnOrder="0">
            <Dynamic dnOrder="0" id="core" value="15"/>
          </Values>
        </Hex>
        <Boolean dnOrder="139" id="TIMER_2_INTERRUPT_ENABLE">
          <Values dnOrder="0">
            <Dynamic dnOrder="0" id="tmr2" value="false"/>
          </Values>
        </Boolean>
        <Boolean dnOrder="140" id="TIMER_2_INTERRUPT_ENABLE_UPDATE">
          <Values dnOrder="0">
            <Dynamic dnOrder="0" id="core" value="true"/>
          </Values>
        </Boolean>
        <String dnOrder="141" id="TIMER_2_INTERRUPT_HANDLER">
          <Values dnOrder="0">
            <Dynamic dnOrder="0" id="tmr2" value="TIMER_2_Handler"/>
          </Values>
        </String>
        <Boolean dnOrder="142" id="TIMER_2_INTERRUPT_HANDLER_LOCK">
          <Values dnOrder="0">
            <Dynamic dnOrder="0" id="tmr2" value="false"/>
          </Values>
        </Boolean>
        <Boolean dnOrder="143" id="TIMER_3_INTERRUPT_ENABLE">
          <Values dnOrder="0">
            <Dynamic dnOrder="0" id="tmr3" value="true"/>
          </Values>
        </Boolean>
        <Boolean dnOrder="144" id="TIMER_3_INTERRUPT_ENABLE_UPDATE">
          <Values dnOrder="0">
            <Dynamic dnOrder="0" id="core" value="false"/>
          </Values>
        </Boolean>
        <String dnOrder="145" id="TIMER_3_INTERRUPT_HANDLER">
          <Values dnOrder="0">
            <Dynamic dnOrder="0" id="tmr3" value="TIMER_3_InterruptHandler"/>
          </Values>
        </String>
        <Boolean dnOrder="146" id="TIMER_3_INTERRUPT_HANDLER_LOCK">
          <Values dnOrder="0">
            <Dynamic dnOrder="0" id="tmr3" value="true"/>
          </Values>
        </Boolean>
        <Boolean dnOrder="147" id="TIMER_4_INTERRUPT_ENABLE">
          <Values dnOrder="0">
            <Dynamic dnOrder="0" id="tmr4" value="true"/>
          </Values>
        </Boolean>
        <Boolean dnOrder="148" id="TIMER_4_INTERRUPT_ENABLE_UPDATE">
          <Values dnOrder="0">
            <Dynamic dnOrder="0" id="core" value="false"/>
          </Values>
        </Boolean>
        <String dnOrder="149" id="TIMER_4_INTERRUPT_HANDLER">
          <Values dnOrder="0">
            <Dynamic dnOrder="0" id="tmr4" value="TIMER_4_InterruptHandler"/>
          </Values>
        </String>
        <Boolean dnOrder="150" id="TIMER_4_INTERRUPT_HANDLER_LOCK">
          <Values dnOrder="0">
            <Dynamic dnOrder="0" id="tmr4" value="true"/>
          </Values>
        </Boolean>
        <Integer dnOrder="151" id="TMR1_CLOCK_FREQUENCY">
          <Values dnOrder="0">
            <Dynamic dnOrder="0" id="core" value="0"/>
          </Values>
        </Integer>
        <Boolean dnOrder="152" id="TMR2_CLOCK_ENABLE">
          <Values dnOrder="0">
            <Dynamic dnOrder="0" id="tmr2" value="true"/>
          </Values>
        </Boolean>
        <Integer dnOrder="153" id="TMR2_CLOCK_FREQUENCY">
          <Values dnOrder="0">
            <Dynamic dnOrder="0" id="core" value="40000000"/>
          </Values>
        </Integer>
        <Boolean dnOrder="154" id="TMR3_CLOCK_ENABLE">
          <Values dnOrder="0">
            <Dynamic dnOrder="0" id="tmr3" value="true"/>
          </Values>
        </Boolean>
        <Integer dnOrder="155" id="TMR3_CLOCK_FREQUENCY">
          <Values dnOrder="0">
            <Dynamic dnOrder="0" id="core" value="40000000"/>
          </Values>
        </Integer>
        <Boolean dnOrder="156" id="TMR4_CLOCK_ENABLE">
          <Values dnOrder="0">
            <Dynamic dnOrder="0" id="tmr4" value="true"/>
          </Values>
        </Boolean>
        <Integer dnOrder="157" id="TMR4_CLOCK_FREQUENCY">
          <Values dnOrder="0">
            <Dynamic dnOrder="0" id="core" value="40000000"/>
          </Values>
        </Integer>
        <Integer dnOrder="158" id="TMR5_CLOCK_FREQUENCY">
          <Values dnOrder="0">
            <Dynamic dnOrder="0" id="core" value="0"/>
          </Values>
        </Integer>
        <Boolean dnOrder="159" id="UART1_CLOCK_ENABLE">
          <Values dnOrder="0">
            <Dynamic dnOrder="0" id="uart1" value="true"/>
          </Values>
        </Boolean>
        <Integer dnOrder="160" id="UART1_CLOCK_FREQUENCY">
          <Values dnOrder="0">
            <Dynamic dnOrder="0" id="core" value="40000000"/>
          </Values>
        </Integer>
        <Integer dnOrder="161" id="UART2_CLOCK_FREQUENCY">
          <Values dnOrder="0">
            <Dynamic dnOrder="0" id="core" value="0"/>
          </Values>
        </Integer>
        <Integer dnOrder="162" id="UART3_CLOCK_FREQUENCY">
          <Values dnOrder="0">
            <Dynamic dnOrder="0" id="core" value="0"/>
          </Values>
        </Integer>
        <Integer dnOrder="163" id="UART4_CLOCK_FREQUENCY">
          <Values dnOrder="0">
            <Dynamic dnOrder="0" id="core" value="0"/>
          </Values>
        </Integer>
        <Integer dnOrder="164" id="UART5_CLOCK_FREQUENCY">
          <Values dnOrder="0">
            <Dynamic dnOrder="0" id="core" value="0"/>
          </Values>
        </Integer>
        <Integer dnOrder="165" id="UART6_CLOCK_FREQUENCY">
          <Values dnOrder="0">
            <Dynamic dnOrder="0" id="core" value="0"/>
          </Values>
        </Integer>
        <Boolean dnOrder="166" id="UART_1_INTERRUPT_ENABLE">
          <Values dnOrder="0">
            <Dynamic dnOrder="0" id="uart1" value="true"/>
          </Values>
        </Boolean>
        <Boolean dnOrder="167" id="UART_1_INTERRUPT_ENABLE_UPDATE">
          <Values dnOrder="0">
            <Dynamic dnOrder="0" id="core" value="false"/>
          </Values>
        </Boolean>
        <String dnOrder="168" id="UART_1_INTERRUPT_HANDLER">
          <Values dnOrder="0">
            <Dynamic dnOrder="0" id="uart1" value="UART_1_InterruptHandler"/>
          </Values>
        </String>
        <Boolean dnOrder="169" id="UART_1_INTERRUPT_HANDLER_LOCK">
          <Values dnOrder="0">
            <Dynamic dnOrder="0" id="uart1" value="true"/>
          </Values>
        </Boolean>
        <Integer dnOrder="170" id="USB_CLOCK_FREQUENCY">
          <Values dnOrder="0">
            <Dynamic dnOrder="0" id="core" value="0"/>
          </Values>
        </Integer>
      </Symbols>
    </UniqueComponent>
    <UniqueComponent dnOrder="2" id="core_timer"/>
    <UniqueComponent dnOrder="3" id="dfp"/>
    <UniqueComponent dnOrder="4" id="i2c2">
      <Symbols dnOrder="0">
        <Integer dnOrder="0" id="BRG_VALUE">
          <Values dnOrder="0">
            <Dynamic dnOrder="0" id="i2c2" value="46"/>
          </Values>
        </Integer>
        <Integer dnOrder="1" id="I2C_CLOCK_FREQ">
          <Values dnOrder="0">
            <Dynamic dnOrder="0" id="i2c2" value="40000000"/>
          </Values>
        </Integer>
        <Long dnOrder="2" id="I2C_CLOCK_SPEED">
          <Values dnOrder="0">
            <User dnOrder="0" value="400000"/>
          </Values>
        </Long>
      </Symbols>
    </UniqueComponent>
    <UniqueComponent dnOrder="5" id="tmr2">
      <Symbols dnOrder="0">
        <Hex dnOrder="0" id="TCON_REG_VALUE">
          <Values dnOrder="0">
            <Dynamic dnOrder="0" id="tmr2" value="120"/>
          </Values>
        </Hex>
        <Comment dnOrder="1" id="TIMER_32BIT_COMMENT">
          <Attributes dnOrder="0">
            <Boolean dnOrder="0" id="visible">
              <Value dnOrder="0">true</Value>
            </Boolean>
          </Attributes>
        </Comment>
        <KeyValueSet dnOrder="2" id="TIMER_32BIT_MODE_SEL">
          <Values dnOrder="0">
            <User dnOrder="0" value="0"/>
          </Values>
        </KeyValueSet>
        <Integer dnOrder="3" id="TIMER_CLOCK_FREQ">
          <Values dnOrder="0">
            <Dynamic dnOrder="0" id="tmr2" value="156250"/>
          </Values>
        </Integer>
        <Long dnOrder="4" id="TIMER_PERIOD">
          <Attributes dnOrder="0">
            <Long dnOrder="0" id="max">
              <Value dnOrder="0">4294967295</Value>
            </Long>
          </Attributes>
          <Values dnOrder="1">
            <Dynamic dnOrder="0" id="tmr2" value="78125"/>
          </Values>
        </Long>
        <KeyValueSet dnOrder="5" id="TIMER_PRE_SCALER">
          <Values dnOrder="0">
            <User dnOrder="0" value="0"/>
          </Values>
        </KeyValueSet>
        <Float dnOrder="6" id="TIMER_TIME_PERIOD_MS">
          <Attributes dnOrder="0">
            <Float dnOrder="0" id="max">
              <Value dnOrder="0">2.748779E7</Value>
            </Float>
          </Attributes>
          <Values dnOrder="1">
            <User dnOrder="0" value="500.0"/>
          </Values>
        </Float>
        <String dnOrder="7" id="TMR_IEC_REG">
          <Values dnOrder="0">
            <Dynamic dnOrder="0" id="tmr2" value="IEC0"/>
          </Values>
        </String>
        <String dnOrder="8" id="TMR_IFS_REG">
          <Values dnOrder="0">
            <Dynamic dnOrder="0" id="tmr2" value="IFS0"/>
          </Values>
        </String>
        <Boolean dnOrder="9" id="TMR_INTERRUPT_MODE">
          <Attributes dnOrder="0">
            <Boolean dnOrder="0" id="visible">
              <Value dnOrder="0">false</Value>
            </Boolean>
          </Attributes>
          <Values dnOrder="1">
            <Dynamic dnOrder="0" id="tmr2" value="false"/>
          </Values>
        </Boolean>
        <Integer dnOrder="10" id="TMR_PRESCALER_VALUE">
          <Values dnOrder="0">
            <Dynamic dnOrder="0" id="tmr2" value="256"/>
          </Values>
        </Integer>
        <Boolean dnOrder="11" id="TMR_SLAVE_INTERRUPT_MODE">
          <Values dnOrder="0">
            <Dynamic dnOrder="0" id="tmr2" value="true"/>
          </Values>
        </Boolean>
      </Symbols>
    </UniqueComponent>
    <UniqueComponent dnOrder="6" id="tmr3">
      <Symbols dnOrder="0">
        <Hex dnOrder="0" id="TCON_REG_VALUE">
          <Values dnOrder="0">
            <Dynamic dnOrder="0" id="tmr3" value="112"/>
          </Values>
        </Hex>
        <Integer dnOrder="1" id="TIMER_CLOCK_FREQ">
          <Attributes dnOrder="0">
            <Boolean dnOrder="0" id="visible">
              <Value dnOrder="0">false</Value>
            </Boolean>
          </Attributes>
          <Values dnOrder="1">
            <Dynamic dnOrder="0" id="tmr3" value="156250"/>
          </Values>
        </Integer>
        <Long dnOrder="2" id="TIMER_PERIOD">
          <Attributes dnOrder="0">
            <Boolean dnOrder="0" id="visible">
              <Value dnOrder="0">false</Value>
            </Boolean>
          </Attributes>
          <Values dnOrder="1">
            <Dynamic dnOrder="0" id="tmr3" value="65535"/>
          </Values>
        </Long>
        <KeyValueSet dnOrder="3" id="TIMER_PRE_SCALER">
          <Attributes dnOrder="0">
            <Boolean dnOrder="0" id="visible">
              <Value dnOrder="0">false</Value>
            </Boolean>
          </Attributes>
          <Values dnOrder="1">
            <User dnOrder="0" value="0"/>
          </Values>
        </KeyValueSet>
        <KeyValueSet dnOrder="4" id="TIMER_SIDL">
          <Attributes dnOrder="0">
            <Boolean dnOrder="0" id="visible">
              <Value dnOrder="0">false</Value>
            </Boolean>
          </Attributes>
        </KeyValueSet>
        <Boolean dnOrder="5" id="TIMER_SLAVE">
          <Values dnOrder="0">
            <Dynamic dnOrder="0" id="tmr3" value="true"/>
          </Values>
        </Boolean>
        <KeyValueSet dnOrder="6" id="TIMER_SRC_SEL">
          <Attributes dnOrder="0">
            <Boolean dnOrder="0" id="visible">
              <Value dnOrder="0">false</Value>
            </Boolean>
          </Attributes>
        </KeyValueSet>
        <Float dnOrder="7" id="TIMER_TIME_PERIOD_MS">
          <Attributes dnOrder="0">
            <Float dnOrder="0" id="max">
              <Value dnOrder="0">419.424</Value>
            </Float>
            <Boolean dnOrder="1" id="visible">
              <Value dnOrder="0">false</Value>
            </Boolean>
          </Attributes>
          <Values dnOrder="1">
            <User dnOrder="0" value="1000.0"/>
          </Values>
        </Float>
        <File dnOrder="8" id="TMR_HEADER1">
          <Attributes dnOrder="0">
            <Boolean dnOrder="0" id="enabled">
              <Value dnOrder="0">false</Value>
            </Boolean>
          </Attributes>
        </File>
        <Boolean dnOrder="9" id="TMR_INTERRUPT_MODE">
          <Values dnOrder="0">
            <Dynamic dnOrder="0" id="tmr3" value="true"/>
          </Values>
        </Boolean>
        <Integer dnOrder="10" id="TMR_PRESCALER_VALUE">
          <Values dnOrder="0">
            <Dynamic dnOrder="0" id="tmr3" value="256"/>
          </Values>
        </Integer>
        <Comment dnOrder="11" id="TMR_SLAVE_COMMENT">
          <Attributes dnOrder="0">
            <Boolean dnOrder="0" id="visible">
              <Value dnOrder="0">true</Value>
            </Boolean>
          </Attributes>
        </Comment>
        <Boolean dnOrder="12" id="TMR_SLAVE_INTERRUPT_MODE">
          <Values dnOrder="0">
            <Dynamic dnOrder="0" id="tmr3" value="true"/>
          </Values>
        </Boolean>
        <File dnOrder="13" id="TMR_SOURCE">
          <Attributes dnOrder="0">
            <Boolean dnOrder="0" id="enabled">
              <Value dnOrder="0">false</Value>
            </Boolean>
          </Attributes>
        </File>
      </Symbols>
    </UniqueComponent>
    <UniqueComponent dnOrder="7" id="tmr4">
      <Symbols dnOrder="0">
        <Hex dnOrder="0" id="TCON_REG_VALUE">
          <Values dnOrder="0">
            <Dynamic dnOrder="0" id="tmr4" value="0"/>
          </Values>
        </Hex>
        <Integer dnOrder="1" id="TIMER_CLOCK_FREQ">
          <Values dnOrder="0">
            <Dynamic dnOrder="0" id="tmr4" value="40000000"/>
          </Values>
        </Integer>
        <Long dnOrder="2" id="TIMER_PERIOD">
          <Values dnOrder="0">
            <Dynamic dnOrder="0" id="tmr4" value="20000"/>
          </Values>
        </Long>
        <KeyValueSet dnOrder="3" id="TIMER_PRE_SCALER">
          <Values dnOrder="0">
            <User dnOrder="0" value="7"/>
          </Values>
        </KeyValueSet>
        <Float dnOrder="4" id="TIMER_TIME_PERIOD_MS">
          <Attributes dnOrder="0">
            <Float dnOrder="0" id="max">
              <Value dnOrder="0">1.638375</Value>
            </Float>
          </Attributes>
          <Values dnOrder="1">
            <User dnOrder="0" value="0.5"/>
          </Values>
        </Float>
        <Boolean dnOrder="5" id="TMR_INTERRUPT_MODE">
          <Values dnOrder="0">
            <Dynamic dnOrder="0" id="tmr4" value="true"/>
          </Values>
        </Boolean>
        <Integer dnOrder="6" id="TMR_PRESCALER_VALUE">
          <Values dnOrder="0">
            <Dynamic dnOrder="0" id="tmr4" value="1"/>
          </Values>
        </Integer>
      </Symbols>
    </UniqueComponent>
    <UniqueComponent dnOrder="8" id="uart1">
      <Symbols dnOrder="0">
        <Integer dnOrder="0" id="BRG_VALUE">
          <Values dnOrder="0">
            <Dynamic dnOrder="0" id="uart1" value="21"/>
          </Values>
        </Integer>
        <KeyValueSet dnOrder="1" id="UART_BRGH">
          <Values dnOrder="0">
            <Dynamic dnOrder="0" id="uart1" value="1"/>
          </Values>
        </KeyValueSet>
        <Integer dnOrder="2" id="UART_CLOCK_FREQ">
          <Values dnOrder="0">
            <Dynamic dnOrder="0" id="uart1" value="40000000"/>
          </Values>
        </Integer>
        <Hex dnOrder="3" id="UMODE_VALUE">
          <Values dnOrder="0">
            <Dynamic dnOrder="0" id="uart1" value="0"/>
          </Values>
        </Hex>
      </Symbols>
    </UniqueComponent>
  </Components>
  <UserData>
    <GraphSettings canvasHeight="400" canvasWidth="400" dnOrder="0"/>
    <ComponentGraph dnOrder="1" id="__ROOTVIEW">
      <ElementPositions dnOrder="0">
        <ElementPosition dnOrder="0" id="adc" x="530" y="337"/>
        <ElementPosition dnOrder="1" id="core" x="241" y="20"/>
        <ElementPosition dnOrder="2" id="core_timer" x="665" y="62"/>
        <ElementPosition dnOrder="3" id="dfp" x="20" y="20"/>
        <ElementPosition dnOrder="4" id="i2c2" x="815" y="65"/>
        <ElementPosition dnOrder="5" id="tmr2" x="350" y="60"/>
        <ElementPosition dnOrder="6" id="tmr3" x="510" y="62"/>
        <ElementPosition dnOrder="7" id="tmr4" x="348" y="151"/>
        <ElementPosition dnOrder="8" id="uart1" x="349" y="319"/>
      </ElementPositions>
    </ComponentGraph>
  </UserData>
</Configuration>
